pyxbar/__init__.py
pyxbar/config.py
pyxbar/menu.py
pyxbar/menu_icons.py
pyxbar/menu_items.py
pyxbar/types.py
pyxbar/utils.py
pyxbar-0.3.30.dist-info/METADATA
pyxbar-0.3.30.dist-info/WHEEL
pyxbar-0.3.30.dist-info/top_level.txt
pyxbar-0.3.30.dist-info/RECORD
