Metadata-Version: 2.1
Name: pyxbar
Version: 0.3.30
Summary: helper functions for xbar menus
Author: Adam Hitchcock
Requires-Python: >=3.9
Requires-Dist: typing-extensions
Requires-Dist: requests
